MANIFEST.in
README.rst
setup.py
bin/hng
hng/__init__.py
hng/__init__.pyc
hng/import_data.py
hng/import_data.pyc
hng/models
hng/predict
hng/preprocess
hng/tf_ae.py
hng.egg-info/PKG-INFO
hng.egg-info/SOURCES.txt
hng.egg-info/dependency_links.txt
hng.egg-info/not-zip-safe
hng.egg-info/requires.txt
hng.egg-info/top_level.txt
hng/models/__init__.py
hng/models/models.py
hng/predict/__init__.py
hng/predict/predict.py
hng/preprocess/__init__.py
hng/preprocess/preprocess.py