Metadata-Version: 1.1
Name: hng
Version: 0.2.0.3.2
Summary: Python package for open-source healthcare machine learning @hngml
Home-page: https://bitbucket.org/HNGML/hng
Author: hngml
Author-email: nilesh.chaudhari@healthnextgen.com
License: MIT
Platform: UNKNOWN
Classifier: Development Status :: 1 - Planning
Classifier: License :: OSI Approved :: MIT License
Classifier: Programming Language :: Python :: 2.7
Classifier: Topic :: Software Development :: Libraries :: Python Modules
